Metadata-Version: 1.0
Name: dsnd-probability-01052020
Version: 0.1
Summary: Gaussian and Binomial distributions
Home-page: UNKNOWN
Author: Sergio Perez
Author-email: sergio.perezcarriche@gmail.com
License: UNKNOWN
Platform: UNKNOWN
